[
  {
    "simplified": "西瓜",
    "traditional": "西瓜",
    "pinyin": "xi1 gua1",
    "definitions": [
      "watermelon",
      "CL:顆|颗[ke1],個|个[ge5]"
    ],
    "addedAt": "2025-04-07T12:36:49.056Z",
    "exampleSentences": [
      "我吃西瓜",
      "我吃西瓜s"
    ]
  },
  {
    "simplified": "呼兰",
    "traditional": "呼蘭",
    "pinyin": "Hu1 lan2",
    "definitions": [
      "Hulan district of Harbin 哈爾濱|哈尔滨[Ha1 er3 bin1] in Heilongjiang"
    ],
    "addedAt": "2025-04-08T13:43:13.475Z",
    "exampleSentences": [
      "呼兰府"
    ]
  },
  {
    "simplified": "五卅运动",
    "traditional": "五卅運動",
    "pinyin": "wu3 sa4 yun4 dong4",
    "definitions": [
      "anti-imperialist movement of 30th May 1925, involving general strike esp. in Shanghai, Guangzhou, Hong Kong etc"
    ],
    "addedAt": "2025-04-08T13:43:15.840Z",
    "exampleSentences": [
      "五卅运动"
    ]
  },
  {
    "simplified": "员",
    "traditional": "員",
    "pinyin": "yuan2",
    "definitions": [
      "(bound form) person engaged in a certain field of activity",
      "(bound form) member",
      "classifier for military generals"
    ],
    "addedAt": "2025-04-08T13:43:20.440Z",
    "exampleSentences": [
      "萧红参加游行，并主动出任宣传员。"
    ]
  },
  {
    "simplified": "转入",
    "traditional": "轉入",
    "pinyin": "zhuan3 ru4",
    "definitions": [
      "to change over to; to shift to; to switch to"
    ],
    "addedAt": "2025-04-08T13:44:03.164Z",
    "exampleSentences": [
      "1925年转入呼兰县第一女子初高两级小学校。"
    ]
  },
  {
    "simplified": "学校",
    "traditional": "學校",
    "pinyin": "xue2 xiao4",
    "definitions": [
      "school",
      "CL:所[suo3]"
    ],
    "addedAt": "2025-04-08T13:45:10.652Z",
    "exampleSentences": [
      "1924年毕业升入北关初高两级小学校女生部上高小。",
      "立第一女子中学校。"
    ]
  },
  {
    "simplified": "荣华",
    "traditional": "榮華",
    "pinyin": "rong2 hua2",
    "definitions": [
      "glory and splendor"
    ],
    "addedAt": "2025-04-08T13:45:12.749Z",
    "exampleSentences": [
      "乳名荣华，学名张秀环，1916年被外祖父姜文选改名为张廼莹。"
    ]
  },
  {
    "simplified": "改名",
    "traditional": "改名",
    "pinyin": "gai3 ming2",
    "definitions": [
      "to rename"
    ],
    "addedAt": "2025-04-08T13:46:10.197Z",
    "exampleSentences": [
      "乳名荣华，学名张秀环，1916年被外祖父姜文选改名为张廼莹。"
    ]
  },
  {
    "simplified": "联合会",
    "traditional": "聯合會",
    "pinyin": "lian2 he2 hui4",
    "definitions": [
      "federation"
    ],
    "addedAt": "2025-04-08T13:46:14.509Z",
    "exampleSentences": [
      "同年7月末，呼兰县学生联合会在西岗公园举办联合义演，以答谢募捐民众，萧红在话剧《傲霜枝》中饰演一位贫苦小姑娘。"
    ]
  },
  {
    "simplified": "家庭",
    "traditional": "家庭",
    "pinyin": "jia1 ting2",
    "definitions": [
      "family",
      "household",
      "CL:戶|户[hu4],個|个[ge4]"
    ],
    "addedAt": "2025-04-08T13:46:31.637Z",
    "exampleSentences": [
      "一个地主家庭。"
    ]
  },
  {
    "simplified": "讲演",
    "traditional": "講演",
    "pinyin": "jiang3 yan3",
    "definitions": [
      "to lecture",
      "to speak publicly"
    ],
    "addedAt": "2025-04-08T13:53:42.248Z",
    "exampleSentences": [
      "期间，呼兰县学生联合会发起游行、募捐、讲演等活动，萧红参加。"
    ]
  },
  {
    "simplified": "发起",
    "traditional": "發起",
    "pinyin": "fa1 qi3",
    "definitions": [
      "to originate",
      "to initiate",
      "to launch (an attack, an initiative etc)",
      "to start",
      "to propose sth (for the first time)"
    ],
    "addedAt": "2025-04-08T13:53:58.765Z",
    "exampleSentences": [
      "期间，呼兰县学生联合会发起游行、募捐、讲演等活动，萧红参加。"
    ]
  },
  {
    "simplified": "兰",
    "traditional": "蘭",
    "pinyin": "Lan2",
    "definitions": [
      "surname Lan",
      "abbr. for Lanzhou 蘭州|兰州[Lan2zhou1], Gansu",
      "orchid (蘭花|兰花 Cymbidium goeringii)",
      "fragrant thoroughwort (蘭草|兰草 Eupatorium fortunei)",
      "lily magnolia (木蘭|木兰)"
    ],
    "addedAt": "2025-04-08T20:58:51.576Z",
    "exampleSentences": [
      "期间，呼兰县学生联合会发起游行、募捐、讲演等活动，萧红参加。"
    ]
  },
  {
    "simplified": "女生",
    "traditional": "女生",
    "pinyin": "nu:3 sheng1",
    "definitions": [
      "schoolgirl",
      "female student",
      "girl"
    ],
    "addedAt": "2025-04-08T20:58:53.893Z",
    "exampleSentences": [
      "1924年毕业升入北关初高两级小学校女生部上高小。"
    ]
  },
  {
    "simplified": "合",
    "traditional": "合",
    "pinyin": "ge3",
    "definitions": [
      "100 ml",
      "one-tenth of a peck",
      "measure for dry grain equal to one-tenth of sheng 升 or liter, or one-hundredth dou 斗",
      "to close",
      "to join",
      "to fit",
      "to be equal to",
      "whole",
      "together",
      "round (in battle)",
      "conjunction (astronomy)",
      "1st note of pentatonic scale",
      "old variant of 盒[he2]",
      "variant of 合[he2]"
    ],
    "addedAt": "2025-04-08T21:00:27.787Z",
    "exampleSentences": [
      "同年7月末，呼兰县学生联合会在西岗公园举办联合义演，以答谢募捐民众，萧红在话剧《傲霜枝》中饰演一位贫苦小姑娘。"
    ]
  },
  {
    "simplified": "演",
    "traditional": "演",
    "pinyin": "yan3",
    "definitions": [
      "to perform (a play etc); to stage (a show)",
      "(bound form) to develop; to play out; to carry out (a task)"
    ],
    "addedAt": "2025-04-08T21:00:29.811Z",
    "exampleSentences": [
      "同年7月末，呼兰县学生联合会在西岗公园举办联合义演，以答谢募捐民众，萧红在话剧《傲霜枝》中饰演一位贫苦小姑娘。"
    ]
  },
  {
    "simplified": "萧红",
    "traditional": "蕭紅",
    "pinyin": "Xiao1 Hong2",
    "definitions": [
      "Xiao Hong (1911-1942), prominent woman writer, originally from Heilongjiang"
    ],
    "addedAt": "2025-04-08T21:02:13.091Z",
    "exampleSentences": [
      "萧红参加游行，并主动出任宣传员。"
    ]
  },
  {
    "simplified": "出任",
    "traditional": "出任",
    "pinyin": "chu1 ren4",
    "definitions": [
      "to take up a post; to start in a new job"
    ],
    "addedAt": "2025-04-08T21:02:50.105Z",
    "exampleSentences": [
      "萧红参加游行，并主动出任宣传员。"
    ]
  },
  {
    "simplified": "贫苦",
    "traditional": "貧苦",
    "pinyin": "pin2 ku3",
    "definitions": [
      "poverty-stricken",
      "poor"
    ],
    "addedAt": "2025-04-08T21:03:43.470Z",
    "exampleSentences": [
      "同年7月末，呼兰县学生联合会在西岗公园举办联合义演，以答谢募捐民众，萧红在话剧《傲霜枝》中饰演一位贫苦小姑娘。"
    ]
  },
  {
    "simplified": "期间",
    "traditional": "期間",
    "pinyin": "qi1 jian1",
    "definitions": [
      "period of time",
      "time",
      "time period",
      "period",
      "CL:個|个[ge4]"
    ],
    "addedAt": "2025-04-08T21:15:55.696Z",
    "exampleSentences": [
      "期间，呼兰县学生联合会发起游行、募捐、讲演等活动，萧红参加。"
    ]
  },
  {
    "simplified": "出生",
    "traditional": "出生",
    "pinyin": "chu1 sheng1",
    "definitions": [
      "to be born"
    ],
    "addedAt": "2025-04-09T00:23:20.153Z",
    "exampleSentences": [
      "出生于"
    ]
  },
  {
    "simplified": "岗子",
    "traditional": "崗子",
    "pinyin": "gang3 zi5",
    "definitions": [
      "mound; hillock",
      "welt (on the skin); ridge (on the road surface etc)"
    ],
    "addedAt": "2025-04-26T02:33:43.764Z",
    "exampleSentences": [
      "乱坟岗子是地主施舍给贫农民们死后的住宅。"
    ]
  },
  {
    "simplified": "弯月",
    "traditional": "彎月",
    "pinyin": "wan1 yue4",
    "definitions": [
      "crescent moon",
      "crescent shape"
    ],
    "addedAt": "2025-04-26T02:33:48.676Z",
    "exampleSentences": [
      "弯月相同弯刀刺上林端。"
    ]
  },
  {
    "simplified": "事情",
    "traditional": "事情",
    "pinyin": "shi4 qing5",
    "definitions": [
      "affair; matter; thing; business",
      "CL:件[jian4],樁|桩[zhuang1]"
    ],
    "addedAt": "2025-04-26T14:33:26.410Z",
    "exampleSentences": [
      "赵三去进城，突然的事情打击着他，使他怎样柔弱呵！"
    ]
  },
  {
    "simplified": "跪",
    "traditional": "跪",
    "pinyin": "gui4",
    "definitions": [
      "to kneel"
    ],
    "addedAt": "2025-04-28T04:59:24.533Z",
    "exampleSentences": [
      "王婆披着散发，幽魂一般的，跪在柴草上，手中的杯子放到嘴边。"
    ]
  },
  {
    "simplified": "后",
    "traditional": "后",
    "pinyin": "Hou4",
    "definitions": [
      "surname Hou",
      "empress",
      "queen",
      "(archaic) monarch",
      "ruler",
      "back",
      "behind",
      "rear",
      "afterwards",
      "after",
      "later",
      "post-"
    ],
    "addedAt": "2025-04-28T05:02:53.151Z",
    "exampleSentences": [
      "王婆散开头发，她走向房后柴栏，在那儿她轻开篱门。"
    ]
  },
  {
    "simplified": "在那儿",
    "traditional": "在那兒",
    "pinyin": "zai4 na5 r5",
    "definitions": [
      "(adverbial expression indicating that the attention of the subject of the verb is focused on what they are doing, not distracted by anything else)",
      "just ...ing (and nothing else)"
    ],
    "addedAt": "2025-04-28T05:19:21.906Z",
    "exampleSentences": [
      "王婆散开头发，她走向房后柴栏，在那儿她轻开篱门。"
    ]
  },
  {
    "simplified": "中国大陆",
    "traditional": "中國大陸",
    "pinyin": "Zhong1 guo2 da4 lu4",
    "definitions": [
      "mainland China"
    ],
    "addedAt": "2025-05-10T21:50:07.925Z",
    "exampleSentences": [
      "中國大陸"
    ]
  },
  {
    "simplified": "常常",
    "traditional": "常常",
    "pinyin": "chang2 chang2",
    "definitions": [
      "frequently; often"
    ],
    "addedAt": "2025-05-13T17:08:28.639Z",
    "exampleSentences": [
      "但活着的农民，常常被地主们驱逐，使他们提着包袱，提着小孩，从破房子再走进更破的房子去。"
    ]
  },
  {
    "simplified": "凄凉",
    "traditional": "悽涼",
    "pinyin": "qi1 liang2",
    "definitions": [
      "mournful; miserable",
      "desolate (place)"
    ],
    "addedAt": "2025-05-13T17:08:32.896Z",
    "exampleSentences": [
      "两条衰乏的腿子，凄凉的挂下，并且摇荡。"
    ]
  },
  {
    "simplified": "女孩",
    "traditional": "女孩",
    "pinyin": "nu:3 hai2",
    "definitions": [
      "girl; lass"
    ],
    "addedAt": "2025-05-13T17:08:38.593Z",
    "exampleSentences": [
      "谁能止住被这小女孩唤起的难忍的酸痛而不哭呢？"
    ]
  },
  {
    "simplified": "妈的",
    "traditional": "媽的",
    "pinyin": "ma1 de5",
    "definitions": [
      "see 他媽的|他妈的[ta1 ma1 de5]"
    ],
    "addedAt": "2025-05-13T17:08:42.740Z",
    "exampleSentences": [
      "她昏迷地忘掉包袱，只顶了一块白布，离开妈妈的门庭。"
    ]
  },
  {
    "simplified": "凄",
    "traditional": "凄",
    "pinyin": "qi1",
    "definitions": [
      "intense cold",
      "frigid",
      "dismal",
      "grim",
      "bleak",
      "sad",
      "mournful",
      "also written 淒|凄[qi1]",
      "variant of 淒|凄[qi1]"
    ],
    "addedAt": "2025-05-14T15:38:01.229Z",
    "exampleSentences": [
      "村人凄静的断续的来看她。"
    ]
  }
]